{
  "swagger": "2.0",
  "info": {
    "title": "Enterprise SaaS API",
    "description": "API Documentation automatically generated by swagger-autogen",
    "version": "1.8.1"
  },
  "basePath": "/",
  "securityDefinitions": {
    "bearerAuth": {
      "type": "apiKey",
      "name": "Authorization",
      "in": "header",
      "description": "Enter your JWT token in the format 'Bearer <token>'"
    }
  },
  "paths": {
    "/": {
      "get": {
        "description": "",
        "responses": {
          "200": {
            "description": "OK"
          }
        }
      }
    },
    "/health": {
      "get": {
        "description": "",
        "responses": {
          "200": {
            "description": "OK"
          }
        }
      }
    },
    "/api/v1/billing/webhook": {
      "post": {
        "description": "",
        "parameters": [
          {
            "name": "stripe-signature",
            "in": "header",
            "type": "string"
          }
        ],
        "responses": {
          "200": {
            "description": "OK"
          },
          "400": {
            "description": "Bad Request"
          }
        }
      }
    },
    "/api/v1/billing/subscribe": {
      "post": {
        "description": "",
        "parameters": [
          {
            "name": "Authorization",
            "in": "header",
            "type": "string"
          },
          {
            "name": "body",
            "in": "body",
            "schema": {
              "type": "object",
              "properties": {
                "priceId": {
                  "example": "any"
                }
              }
            }
          }
        ],
        "responses": {
          "200": {
            "description": "OK"
          }
        }
      }
    },
    "/api/v1/billing/portal": {
      "post": {
        "description": "",
        "parameters": [
          {
            "name": "Authorization",
            "in": "header",
            "type": "string"
          }
        ],
        "responses": {
          "200": {
            "description": "OK"
          }
        }
      }
    },
    "/api/v1/auth/register": {
      "post": {
        "description": "",
        "parameters": [
          {
            "name": "body",
            "in": "body",
            "schema": {
              "type": "object",
              "properties": {
                "email": {
                  "example": "any"
                },
                "password": {
                  "example": "any"
                },
                "fullName": {
                  "example": "any"
                }
              }
            }
          }
        ],
        "responses": {
          "201": {
            "description": "Created"
          }
        }
      }
    },
    "/api/v1/auth/login": {
      "post": {
        "description": "",
        "parameters": [
          {
            "name": "user-agent",
            "in": "header",
            "type": "string"
          },
          {
            "name": "body",
            "in": "body",
            "schema": {
              "type": "object",
              "properties": {
                "email": {
                  "example": "any"
                },
                "password": {
                  "example": "any"
                }
              }
            }
          }
        ],
        "responses": {
          "200": {
            "description": "OK"
          }
        }
      }
    },
    "/api/v1/auth/refresh-token": {
      "post": {
        "description": "",
        "parameters": [
          {
            "name": "body",
            "in": "body",
            "schema": {
              "type": "object",
              "properties": {
                "refreshToken": {
                  "example": "any"
                }
              }
            }
          }
        ],
        "responses": {
          "200": {
            "description": "OK"
          }
        }
      }
    },
    "/api/v1/auth/accept-invite": {
      "post": {
        "description": "",
        "parameters": [
          {
            "name": "body",
            "in": "body",
            "schema": {
              "type": "object",
              "properties": {
                "token": {
                  "example": "any"
                },
                "fullName": {
                  "example": "any"
                },
                "password": {
                  "example": "any"
                }
              }
            }
          }
        ],
        "responses": {
          "201": {
            "description": "Created"
          }
        }
      }
    },
    "/api/v1/auth/forgot-password": {
      "post": {
        "description": "",
        "parameters": [
          {
            "name": "body",
            "in": "body",
            "schema": {
              "type": "object",
              "properties": {
                "email": {
                  "example": "any"
                }
              }
            }
          }
        ],
        "responses": {
          "200": {
            "description": "OK"
          }
        }
      }
    },
    "/api/v1/auth/reset-password": {
      "post": {
        "description": "",
        "parameters": [
          {
            "name": "body",
            "in": "body",
            "schema": {
              "type": "object",
              "properties": {
                "token": {
                  "example": "any"
                },
                "newPassword": {
                  "example": "any"
                }
              }
            }
          }
        ],
        "responses": {
          "200": {
            "description": "OK"
          }
        }
      }
    },
    "/api/v1/auth/me": {
      "get": {
        "description": "",
        "parameters": [
          {
            "name": "Authorization",
            "in": "header",
            "type": "string"
          }
        ],
        "responses": {
          "200": {
            "description": "OK"
          }
        }
      }
    },
    "/api/v1/users/me/avatar": {
      "post": {
        "description": "",
        "parameters": [
          {
            "name": "Authorization",
            "in": "header",
            "type": "string"
          }
        ],
        "responses": {
          "200": {
            "description": "OK"
          }
        }
      }
    },
    "/api/v1/products/": {
      "post": {
        "description": "",
        "parameters": [
          {
            "name": "user-agent",
            "in": "header",
            "type": "string"
          }
        ],
        "responses": {
          "201": {
            "description": "Created"
          }
        }
      },
      "get": {
        "description": "",
        "responses": {
          "200": {
            "description": "OK"
          }
        }
      }
    },
    "/api/v1/products/{id}": {
      "delete": {
        "description": "",
        "parameters": [
          {
            "name": "id",
            "in": "path",
            "required": true,
            "type": "string"
          }
        ],
        "responses": {
          "200": {
            "description": "OK"
          }
        }
      }
    },
    "/api/v1/organizations/invite": {
      "post": {
        "description": "",
        "parameters": [
          {
            "name": "body",
            "in": "body",
            "schema": {
              "type": "object",
              "properties": {
                "email": {
                  "example": "any"
                },
                "role": {
                  "example": "any"
                }
              }
            }
          }
        ],
        "responses": {
          "201": {
            "description": "Created"
          }
        }
      }
    }
  },
  "security": [
    {
      "bearerAuth": []
    }
  ]
}